Workbook

Sheet Sales Data
A1: Sales & Revenue — Raw Transaction Data (FY 2024)
A2: Order ID | B2: Month | C2: Quarter | D2: Region | E2: Sales Rep | F2: Category | G2: Product | H2: Units Sold | I2: Unit Price (₹) | J2: Gross Revenue (₹) | K2: Discount (%) | L2: Discount Amount (₹) | M2: Net Revenue (₹)
A3: ORD-1001 | B3: Jan | C3: Q1 | D3: East | E3: Sneha Iyer | F3: Electronics | G3: Laptop Pro | H3: 8 | I3: 28407.06 | J3: =H3*I3 -> 227256.48 | K3: 0 | L3: =J3*K3 -> 0 | M3: =J3-L3 -> 227256.48
A4: ORD-1002 | B4: Jan | C4: Q1 | D4: West | E4: Arjun Mehta | F4: Beauty | G4: Face Serum | H4: 1 | I4: 619.96 | J4: =H4*I4 -> 619.96 | K4: 0 | L4: =J4*K4 -> 0 | M4: =J4-L4 -> 619.96
A5: ORD-1003 | B5: Jan | C5: Q1 | D5: North | E5: Vikram Das | F5: Beauty | G5: Moisturiser | H5: 7 | I5: 1018.25 | J5: =H5*I5 -> 7127.75 | K5: 0.15 | L5: =J5*K5 -> 1069.1625 | M5: =J5-L5 -> 6058.5875
A6: ORD-1004 | B6: Jan | C6: Q1 | D6: South | E6: Anjali Singh | F6: Beauty | G6: Sunscreen SPF50 | H6: 19 | I6: 738.04 | J6: =H6*I6 -> 14022.76 | K6: 0.2 | L6: =J6*K6 -> 2804.552 | M6: =J6-L6 -> 11218.208
A7: ORD-1005 | B7: Jan | C7: Q1 | D7: West | E7: Divya Nair | F7: Electronics | G7: Wireless Earbuds | H7: 9 | I7: 28853.43 | J7: =H7*I7 -> 259680.87 | K7: 0.2 | L7: =J7*K7 -> 51936.174 | M7: =J7-L7 -> 207744.7
A8: ORD-1006 | B8: Jan | C8: Q1 | D8: North | E8: Rohan Gupta | F8: Home & Living | G8: Coffee Maker | H8: 4 | I8: 4442.33 | J8: =H8*I8 -> 17769.32 | K8: 0 | L8: =J8*K8 -> 0 | M8: =J8-L8 -> 17769.32
A9: ORD-1007 | B9: Jan | C9: Q1 | D9: North | E9: Anjali Singh | F9: Beauty | G9: Hair Dryer | H9: 18 | I9: 639.89 | J9: =H9*I9 -> 11518.02 | K9: 0.05 | L9: =J9*K9 -> 575.901 | M9: =J9-L9 -> 10942.119
A10: ORD-1008 | B10: Jan | C10: Q1 | D10: East | E10: Meera Joshi | F10: Electronics | G10: Tablet | H10: 12 | I10: 40665.86 | J10: =H10*I10 -> 487990.32 | K10: 0.15 | L10: =J10*K10 -> 73198.548 | M10: =J10-L10 -> 414791.77
A11: ORD-1009 | B11: Jan | C11: Q1 | D11: South | E11: Karan Patel | F11: Electronics | G11: Laptop Pro | H11: 3 | I11: 48448.9 | J11: =H11*I11 -> 145346.7 | K11: 0.2 | L11: =J11*K11 -> 29069.34 | M11: =J11-L11 -> 116277.36
A12: ORD-1010 | B12: Jan | C12: Q1 | D12: East | E12: Anjali Singh | F12: Electronics | G12: 4K Monitor | H12: 12 | I12: 29054.31 | J12: =H12*I12 -> 348651.72 | K12: 0 | L12: =J12*K12 -> 0 | M12: =J12-L12 -> 348651.72
A13: ORD-1011 | B13: Jan | C13: Q1 | D13: North | E13: Meera Joshi | F13: Clothing | G13: Casual T-Shirt | H13: 6 | I13: 2818.28 | J13: =H13*I13 -> 16909.68 | K13: 0 | L13: =J13*K13 -> 0 | M13: =J13-L13 -> 16909.68
A14: ORD-1012 | B14: Jan | C14: Q1 | D14: West | E14: Karan Patel | F14: Clothing | G14: Winter Coat | H14: 18 | I14: 2189.23 | J14: =H14*I14 -> 39406.14 | K14: 0 | L14: =J14*K14 -> 0 | M14: =J14-L14 -> 39406.14
... A255: ORD-1253 | B255: Dec | C255: Q4 | D255: East | E255: Arjun Mehta | F255: Clothing | G255: Casual T-Shirt | H255: 11 | I255: 2296.43 | J255: =H255*I255 -> 25260.73 | K255: 0.2 | L255: =J255*K255 -> 5052.146 | M255: =J255-L255 -> 20208.584
A256: TOTAL | H256: =SUM(H3:H255) -> 2506 | J256: =SUM(J3:J255) -> 21646397 | L256: =SUM(L3:L255) -> 1422210.2 | M256: =SUM(M3:M255) -> 20224187

Sheet Monthly Summary
A1: Monthly Sales Summary — FY 2024
A2: Month | B2: Quarter | C2: Orders | D2: Units Sold | E2: Gross Revenue (₹) | F2: Net Revenue (₹) | G2: Avg Order Value (₹)
A3: Jan | B3: Q1 | C3: =COUNTIF('Sales Data'!B:B,A3) -> 25 | D3: =SUMIF('Sales Data'!B:B,A3,'Sales Data'!H:H) -> 257 | E3: =SUMIF('Sales Data'!B:B,A3,'Sales Data'!J:J) -> 2336597.5 | F3: =SUMIF('Sales Data'!B:B,A3,'Sales Data'!M:M) -> 2164277.1 | G3: =IFERROR(F3/C3,0) -> 86571.082
A4: Feb | B4: Q1 | C4: =COUNTIF('Sales Data'!B:B,A4) -> 19 | D4: =SUMIF('Sales Data'!B:B,A4,'Sales Data'!H:H) -> 197 | E4: =SUMIF('Sales Data'!B:B,A4,'Sales Data'!J:J) -> 1335069.5 | F4: =SUMIF('Sales Data'!B:B,A4,'Sales Data'!M:M) -> 1174613.2 | G4: =IFERROR(F4/C4,0) -> 61821.745
A5: Mar | B5: Q1 | C5: =COUNTIF('Sales Data'!B:B,A5) -> 18 | D5: =SUMIF('Sales Data'!B:B,A5,'Sales Data'!H:H) -> 181 | E5: =SUMIF('Sales Data'!B:B,A5,'Sales Data'!J:J) -> 1488808.9 | F5: =SUMIF('Sales Data'!B:B,A5,'Sales Data'!M:M) -> 1446848.9 | G5: =IFERROR(F5/C5,0) -> 80380.495
A6: Apr | B6: Q2 | C6: =COUNTIF('Sales Data'!B:B,A6) -> 15 | D6: =SUMIF('Sales Data'!B:B,A6,'Sales Data'!H:H) -> 188 | E6: =SUMIF('Sales Data'!B:B,A6,'Sales Data'!J:J) -> 1147551.6 | F6: =SUMIF('Sales Data'!B:B,A6,'Sales Data'!M:M) -> 1025029.8 | G6: =IFERROR(F6/C6,0) -> 68335.319
A7: May | B7: Q2 | C7: =COUNTIF('Sales Data'!B:B,A7) -> 22 | D7: =SUMIF('Sales Data'!B:B,A7,'Sales Data'!H:H) -> 204 | E7: =SUMIF('Sales Data'!B:B,A7,'Sales Data'!J:J) -> 2142133.3 | F7: =SUMIF('Sales Data'!B:B,A7,'Sales Data'!M:M) -> 2005790.8 | G7: =IFERROR(F7/C7,0) -> 91172.311
A8: Jun | B8: Q2 | C8: =COUNTIF('Sales Data'!B:B,A8) -> 24 | D8: =SUMIF('Sales Data'!B:B,A8,'Sales Data'!H:H) -> 257 | E8: =SUMIF('Sales Data'!B:B,A8,'Sales Data'!J:J) -> 2000131.9 | F8: =SUMIF('Sales Data'!B:B,A8,'Sales Data'!M:M) -> 1940719.5 | G8: =IFERROR(F8/C8,0) -> 80863.313
A9: Jul | B9: Q3 | C9: =COUNTIF('Sales Data'!B:B,A9) -> 24 | D9: =SUMIF('Sales Data'!B:B,A9,'Sales Data'!H:H) -> 249 | E9: =SUMIF('Sales Data'!B:B,A9,'Sales Data'!J:J) -> 1299352 | F9: =SUMIF('Sales Data'!B:B,A9,'Sales Data'!M:M) -> 1227908 | G9: =IFERROR(F9/C9,0) -> 51162.833
A10: Aug | B10: Q3 | C10: =COUNTIF('Sales Data'!B:B,A10) -> 23 | D10: =SUMIF('Sales Data'!B:B,A10,'Sales Data'!H:H) -> 204 | E10: =SUMIF('Sales Data'!B:B,A10,'Sales Data'!J:J) -> 2794878 | F10: =SUMIF('Sales Data'!B:B,A10,'Sales Data'!M:M) -> 2585682.2 | G10: =IFERROR(F10/C10,0) -> 112420.96
A11: Sep | B11: Q3 | C11: =COUNTIF('Sales Data'!B:B,A11) -> 25 | D11: =SUMIF('Sales Data'!B:B,A11,'Sales Data'!H:H) -> 223 | E11: =SUMIF('Sales Data'!B:B,A11,'Sales Data'!J:J) -> 1098249.4 | F11: =SUMIF('Sales Data'!B:B,A11,'Sales Data'!M:M) -> 1055042 | G11: =IFERROR(F11/C11,0) -> 42201.681
A12: Oct | B12: Q4 | C12: =COUNTIF('Sales Data'!B:B,A12) -> 19 | D12: =SUMIF('Sales Data'!B:B,A12,'Sales Data'!H:H) -> 171 | E12: =SUMIF('Sales Data'!B:B,A12,'Sales Data'!J:J) -> 1900286 | F12: =SUMIF('Sales Data'!B:B,A12,'Sales Data'!M:M) -> 1794969.8 | G12: =IFERROR(F12/C12,0) -> 94472.096
A13: Nov | B13: Q4 | C13: =COUNTIF('Sales Data'!B:B,A13) -> 20 | D13: =SUMIF('Sales Data'!B:B,A13,'Sales Data'!H:H) -> 214 | E13: =SUMIF('Sales Data'!B:B,A13,'Sales Data'!J:J) -> 2689801.1 | F13: =SUMIF('Sales Data'!B:B,A13,'Sales Data'!M:M) -> 2492352 | G13: =IFERROR(F13/C13,0) -> 124617.6
A14: Dec | B14: Q4 | C14: =COUNTIF('Sales Data'!B:B,A14) -> 19 | D14: =SUMIF('Sales Data'!B:B,A14,'Sales Data'!H:H) -> 161 | E14: =SUMIF('Sales Data'!B:B,A14,'Sales Data'!J:J) -> 1413537.8 | F14: =SUMIF('Sales Data'!B:B,A14,'Sales Data'!M:M) -> 1310953.3 | G14: =IFERROR(F14/C14,0) -> 68997.541
A15: FULL YEAR | C15: =SUM(C3:C14) -> 253 | D15: =SUM(D3:D14) -> 2506 | E15: =SUM(E3:E14) -> 21646397 | F15: =SUM(F3:F14) -> 20224187 | G15: =SUM(G3:G14) -> 963016.98

Sheet Category Analysis
A1: Revenue by Category — FY 2024
A2: Category | B2: Orders | C2: Units Sold | D2: Gross Revenue (₹) | E2: Net Revenue (₹) | F2: % of Total Revenue
A3: Electronics | B3: =COUNTIF('Sales Data'!F:F,A3) -> 46 | C3: =SUMIF('Sales Data'!F:F,A3,'Sales Data'!H:H) -> 464 | D3: =SUMIF('Sales Data'!F:F,A3,'Sales Data'!J:J) -> 16867807 | E3: =SUMIF('Sales Data'!F:F,A3,'Sales Data'!M:M) -> 15807710 | F3: =IFERROR(E3/SUM(E3:E7),0) -> 0.78162403
A4: Clothing | B4: =COUNTIF('Sales Data'!F:F,A4) -> 43 | C4: =SUMIF('Sales Data'!F:F,A4,'Sales Data'!H:H) -> 354 | D4: =SUMIF('Sales Data'!F:F,A4,'Sales Data'!J:J) -> 986491.51 | E4: =SUMIF('Sales Data'!F:F,A4,'Sales Data'!M:M) -> 907584.23 | F4: =IFERROR(E4/SUM(E3:E7),0) -> 0.04487618
A5: Home & Living | B5: =COUNTIF('Sales Data'!F:F,A5) -> 55 | C5: =SUMIF('Sales Data'!F:F,A5,'Sales Data'!H:H) -> 493 | D5: =SUMIF('Sales Data'!F:F,A5,'Sales Data'!J:J) -> 2489066.2 | E5: =SUMIF('Sales Data'!F:F,A5,'Sales Data'!M:M) -> 2300968.4 | F5: =IFERROR(E5/SUM(E3:E7),0) -> 0.1137731
A6: Sports | B6: =COUNTIF('Sales Data'!F:F,A6) -> 54 | C6: =SUMIF('Sales Data'!F:F,A6,'Sales Data'!H:H) -> 611 | D6: =SUMIF('Sales Data'!F:F,A6,'Sales Data'!J:J) -> 807971.61 | E6: =SUMIF('Sales Data'!F:F,A6,'Sales Data'!M:M) -> 751344.73 | F6: =IFERROR(E6/SUM(E3:E7),0) -> 0.037150801
A7: Beauty | B7: =COUNTIF('Sales Data'!F:F,A7) -> 55 | C7: =SUMIF('Sales Data'!F:F,A7,'Sales Data'!H:H) -> 584 | D7: =SUMIF('Sales Data'!F:F,A7,'Sales Data'!J:J) -> 495060.56 | E7: =SUMIF('Sales Data'!F:F,A7,'Sales Data'!M:M) -> 456578.9 | F7: =IFERROR(E7/SUM(E3:E7),0) -> 0.022575884
A8: TOTAL | B8: =SUM(B3:B7) -> 253 | C8: =SUM(C3:C7) -> 2506 | D8: =SUM(D3:D7) -> 21646397 | E8: =SUM(E3:E7) -> 20224187 | F8: =SUM(F3:F7) -> 1

Sheet Region Analysis
A1: Revenue by Region — FY 2024
A2: Region | B2: Orders | C2: Units Sold | D2: Gross Revenue (₹) | E2: Net Revenue (₹) | F2: % of Total Revenue
A3: North | B3: =COUNTIF('Sales Data'!D:D,A3) -> 62 | C3: =SUMIF('Sales Data'!D:D,A3,'Sales Data'!H:H) -> 614 | D3: =SUMIF('Sales Data'!D:D,A3,'Sales Data'!J:J) -> 3754096.7 | E3: =SUMIF('Sales Data'!D:D,A3,'Sales Data'!M:M) -> 3547200 | F3: =IFERROR(E3/SUM(E3:E6),0) -> 0.17539395
A4: South | B4: =COUNTIF('Sales Data'!D:D,A4) -> 59 | C4: =SUMIF('Sales Data'!D:D,A4,'Sales Data'!H:H) -> 543 | D4: =SUMIF('Sales Data'!D:D,A4,'Sales Data'!J:J) -> 3678275.5 | E4: =SUMIF('Sales Data'!D:D,A4,'Sales Data'!M:M) -> 3512764.8 | F4: =IFERROR(E4/SUM(E3:E6),0) -> 0.17369128
A5: East | B5: =COUNTIF('Sales Data'!D:D,A5) -> 65 | C5: =SUMIF('Sales Data'!D:D,A5,'Sales Data'!H:H) -> 633 | D5: =SUMIF('Sales Data'!D:D,A5,'Sales Data'!J:J) -> 5848662.5 | E5: =SUMIF('Sales Data'!D:D,A5,'Sales Data'!M:M) -> 5398221.1 | F5: =IFERROR(E5/SUM(E3:E6),0) -> 0.26691907
A6: West | B6: =COUNTIF('Sales Data'!D:D,A6) -> 67 | C6: =SUMIF('Sales Data'!D:D,A6,'Sales Data'!H:H) -> 716 | D6: =SUMIF('Sales Data'!D:D,A6,'Sales Data'!J:J) -> 8365362.1 | E6: =SUMIF('Sales Data'!D:D,A6,'Sales Data'!M:M) -> 7766000.7 | F6: =IFERROR(E6/SUM(E3:E6),0) -> 0.3839957
A7: TOTAL | B7: =SUM(B3:B6) -> 253 | C7: =SUM(C3:C6) -> 2506 | D7: =SUM(D3:D6) -> 21646397 | E7: =SUM(E3:E6) -> 20224187 | F7: =SUM(F3:F6) -> 1

Sheet KPI Summary
A1: KPI Summary — FY 2024
A2: KPI | B2: Value | C2: Notes
A3: Total Orders | B3: =COUNTA('Sales Data'!A3:A10000)-1 -> 253 | C3: Count of all transactions
A4: Total Units Sold | B4: =SUM('Sales Data'!H:H) -> 5012 | C4: Sum of units sold
A5: Gross Revenue (₹) | B5: =SUM('Sales Data'!J:J) -> 43292794 | C5: Before discounts
A6: Total Discounts (₹) | B6: =SUM('Sales Data'!L:L) -> 2844420.4 | C6: Discount amount given
A7: Net Revenue (₹) | B7: =SUM('Sales Data'!M:M) -> 40448373 | C7: After discounts
A8: Avg Order Value (₹) | B8: =IFERROR(B6/B3,0) -> 11242.768 | C8: Net Rev / Orders
A9: Best Month | B9: =INDEX('Monthly Summary'!A3:A14,MATCH(MAX('Monthly Summary'!F3:F14),'Monthly Summary'!F3:F14,0)) -> Aug | C9: Highest net revenue month
A10: Top Category | B10: =INDEX('Category Analysis'!A3:A7,MATCH(MAX('Category Analysis'!E3:E7),'Category Analysis'!E3:E7,0)) -> Electronics | C10: By net revenue
A11: Top Region | B11: =INDEX('Region Analysis'!A3:A6,MATCH(MAX('Region Analysis'!E3:E6),'Region Analysis'!E3:E6,0)) -> West | C11: By net revenue
